{
    "sessionChartList" : [
        {
            "id": 1,
            "name": "Position over time",
            "shortName": "positionOverTime"
        },
        {
            "id": 2,
            "name": "Demographics",
            "shortName": "demographics"
        },
        {
            "id": 3,
            "name": "Parallel Sets",
            "shortName": "parallelSets"
        }
    ],
    "studyChartList" : [
        {
            "id": 4,
            "name": "Visitor demographics",
            "shortName": "visitorDemographics"
        }
    ]
}